fek_extractor/__init__.py
fek_extractor/__main__.py
fek_extractor/cli.py
fek_extractor/core.py
fek_extractor/metrics.py
fek_extractor/models.py
fek_extractor/debug/__main__.py
fek_extractor/io/__init__.py
fek_extractor/io/exports.py
fek_extractor/io/pdf.py
fek_extractor/parsing/__init__.py
fek_extractor/parsing/articles.py
fek_extractor/parsing/articles_norm.py
fek_extractor/parsing/dates.py
fek_extractor/parsing/headers.py
fek_extractor/parsing/heuristics.py
fek_extractor/parsing/html.py
fek_extractor/parsing/html_blocks.py
fek_extractor/parsing/normalize.py
fek_extractor/parsing/title_fixups.py
fek_extractor/parsing/titles.py
fek_extractor/parsing/rules/__init__.py
fek_extractor/parsing/rules/shared.py
fek_extractor/utils/__init__.py
fek_extractor/utils/html_cleanup.py
fek_extractor/utils/logging.py
fek_extractor/utils/text.py
fek_extractor-0.1.0.dist-info/licenses/LICENSE
fek_extractor-0.1.0.dist-info/licenses/NOTICE
fek_extractor-0.1.0.dist-info/METADATA
fek_extractor-0.1.0.dist-info/WHEEL
fek_extractor-0.1.0.dist-info/entry_points.txt
fek_extractor-0.1.0.dist-info/top_level.txt
fek_extractor-0.1.0.dist-info/RECORD
