Metadata-Version: 2.4
Name: fek-extractor
Version: 0.1.0
Summary: Extract structured data from FEK PDFs.
Author-email: "Dimitrios S. Sfyris" <info@aspectsoft.gr>
License-Expression: Apache-2.0
Project-URL: Homepage, https://github.com/dmsfiris/fek-extractor
Project-URL: Repository, https://github.com/dmsfiris/fek-extractor
Project-URL: Issues, https://github.com/dmsfiris/fek-extractor/issues
Project-URL: Changelog, https://github.com/dmsfiris/fek-extractor/blob/master/CHANGELOG.md
Keywords: FEK,Greek,Government Gazette,NLP,PDF,information extraction
Classifier: Programming Language :: Python :: 3
Classifier: Programming Language :: Python :: 3.10
Classifier: Programming Language :: Python :: 3.11
Classifier: Programming Language :: Python :: 3.12
Classifier: Operating System :: OS Independent
Classifier: Natural Language :: Greek
Classifier: Topic :: Text Processing :: Linguistic
Classifier: Intended Audience :: Developers
Requires-Python: >=3.10
License-File: LICENSE
License-File: NOTICE
Requires-Dist: pdfminer.six>=20221105
Requires-Dist: beautifulsoup4>=4.12
Provides-Extra: dev
Requires-Dist: pytest>=8; extra == "dev"
Requires-Dist: pytest-cov>=5; extra == "dev"
Requires-Dist: ruff>=0.5; extra == "dev"
Requires-Dist: black>=24.8; extra == "dev"
Requires-Dist: mypy>=1.10; extra == "dev"
Requires-Dist: pre-commit>=3.7; extra == "dev"
Requires-Dist: mkdocs>=1.5; extra == "dev"
Requires-Dist: mkdocs-material>=9.5; extra == "dev"
Requires-Dist: build>=1.2.1; extra == "dev"
Requires-Dist: types-beautifulsoup4>=4.12; extra == "dev"
Dynamic: license-file
